gradle.properties
hexdoc_hexcassettes/__gradle_version__.py
hexdoc_hexcassettes/__init__.py
hexdoc_hexcassettes/__version__.py
hexdoc_hexcassettes/_hooks.py
hexdoc_hexcassettes/py.typed
hexdoc_hexcassettes/_export/.gitignore
hexdoc_hexcassettes/_export/__init__.py
hexdoc_hexcassettes/_export/generated/__init__.py
hexdoc_hexcassettes/_export/generated/hexcassettes.hexdoc.json
hexdoc_hexcassettes/_export/generated/hexcassettes.patterns.hexdoc.json
hexdoc_hexcassettes/_export/generated/assets/hexcassettes/lang/en_us.json
hexdoc_hexcassettes/_export/generated/assets/hexcassettes/lang/zh_cn.json
hexdoc_hexcassettes/_export/generated/assets/hexcassettes/models/item/cassette.json
hexdoc_hexcassettes/_export/generated/assets/hexcassettes/textures/cassette.png
hexdoc_hexcassettes/_export/generated/assets/hexcassettes/textures/item/cassette.png
hexdoc_hexcassettes/_export/generated/assets/hexcasting/lang/en_us.flatten.json5
hexdoc_hexcassettes/_export/generated/assets/hexcasting/patchouli_books/thehexbook/en_us/entries/async.json
hexdoc_hexcassettes/_export/generated/data/hexcassettes/recipes/cassette.json
hexdoc_hexcassettes/_templates/__init__.py
hexdoc_hexcassettes/_templates/index.css.jinja
hexdoc_hexcassettes-1.1.4.1.0.0.dist-info/METADATA
hexdoc_hexcassettes-1.1.4.1.0.0.dist-info/WHEEL
hexdoc_hexcassettes-1.1.4.1.0.0.dist-info/entry_points.txt
hexdoc_hexcassettes-1.1.4.1.0.0.dist-info/licenses/LICENSE
hexdoc_hexcassettes-1.1.4.1.0.0.dist-info/RECORD
