Metadata-Version: 2.4
Name: hexdoc-hexcassettes
Version: 1.1.4.1.0.0
Summary: Python web book docgen and hexdoc plugin for Hexcassettes.
Project-URL: Homepage, https://miyucomics.github.io/hexcassettes/
Project-URL: Source, https://github.com/miyucomics/hexcassettes
Author: miyucomics
License-File: LICENSE
Keywords: hexdoc
Requires-Python: >=3.11
Requires-Dist: hexdoc-hexcasting~=0.11.2.1.0.dev20
Provides-Extra: dev
Requires-Dist: ruff~=0.1.4; extra == 'dev'
